stocks_earnings_dates/__init__.py
stocks_earnings_dates/core.py
stocks_earnings_dates/data/earnings.db
stocks_earnings_dates-0.1.6.dist-info/METADATA
stocks_earnings_dates-0.1.6.dist-info/WHEEL
stocks_earnings_dates-0.1.6.dist-info/top_level.txt
stocks_earnings_dates-0.1.6.dist-info/RECORD
