Metadata-Version: 2.4
Name: stocks-earnings-dates
Version: 0.1.6
Summary: Access 10 years of historical earnings dates for S&P 500 and Nasdaq stocks.
Author-email: AlbertPerez7 <albertperez2004@gmail.com>
Requires-Python: >=3.9
Requires-Dist: pandas<3.0.0,>=2.3.1
Requires-Dist: yfinance<0.3.0,>=0.2.65
